MANIFEST.in
README
requirements.txt
setup.cfg
setup.py
hyperstream/__init__.py
hyperstream/client.py
hyperstream/config.py
hyperstream/hyperstream.py
hyperstream/online_engine.py
hyperstream/plugin_manager.py
hyperstream/session.py
hyperstream/time_interval.py
hyperstream/version.py
hyperstream.egg-info/PKG-INFO
hyperstream.egg-info/SOURCES.txt
hyperstream.egg-info/dependency_links.txt
hyperstream.egg-info/requires.txt
hyperstream.egg-info/top_level.txt
hyperstream/channels/__init__.py
hyperstream/channels/assets_channel.py
hyperstream/channels/assets_file_channel.py
hyperstream/channels/base_channel.py
hyperstream/channels/channel_manager.py
hyperstream/channels/database_channel.py
hyperstream/channels/file_channel.py
hyperstream/channels/memory_channel.py
hyperstream/channels/module_channel.py
hyperstream/channels/tool_channel.py
hyperstream/factor/__init__.py
hyperstream/factor/factor.py
hyperstream/itertools2/__init__.py
hyperstream/itertools2/itertools2.py
hyperstream/meta_data/__init__.py
hyperstream/meta_data/meta_data_manager.py
hyperstream/models/__init__.py
hyperstream/models/factor.py
hyperstream/models/meta_data.py
hyperstream/models/node.py
hyperstream/models/plate.py
hyperstream/models/session.py
hyperstream/models/stream.py
hyperstream/models/time_interval.py
hyperstream/models/tool.py
hyperstream/models/workflow.py
hyperstream/node/__init__.py
hyperstream/node/node.py
hyperstream/plate/__init__.py
hyperstream/plate/plate.py
hyperstream/plate/plate_manager.py
hyperstream/stream/__init__.py
hyperstream/stream/stream.py
hyperstream/stream/stream_collections.py
hyperstream/stream/stream_id.py
hyperstream/stream/stream_instance.py
hyperstream/stream/stream_view.py
hyperstream/tool/__init__.py
hyperstream/tool/aggregate_tool.py
hyperstream/tool/base_tool.py
hyperstream/tool/multi_output_tool.py
hyperstream/tool/plate_creation_tool.py
hyperstream/tool/selector_tool.py
hyperstream/tool/tool.py
hyperstream/tools/__init__.py
hyperstream/tools/aggregate/2016-10-26_v0.1.0.py
hyperstream/tools/aggregate/__init__.py
hyperstream/tools/aggregate_into_dict_and_apply/2017-05-26_v0.0.1.py
