Metadata-Version: 1.0
Name: hyperstream
Version: 0.3.8
Summary: Hyperstream is a large-scale, flexible and robust software package for processing streaming data
Home-page: https://irc-sphere.github.io/HyperStream/
Author: Tom Diethe; Meelis Kull; Niall Twomey; Kacper Sokol; Hao Song; Miquel Perello-Nieto; Emma Tonkin; Peter Flach
Author-email: hyperstreamhq@googlegroups.com
License: MIT
Platform: UNKNOWN
